{
  "type": "Feature",
  "id": "facility:0-20000-0-45004",
  "geometry": {
    "type": "Point",
    "coordinates": [
      114.1727777778,
      22.3119444444,
      64.8
    ]
  },
  "time": {
    "interval": [
      "1951-06-01",
      ".."
    ]
  },
  "conformsTo": [
    "http://wigos.wmo.int/spec/wmdr/2/conf/core"
  ],
  "properties": {
    "type": "facility",
    "title": "KOWLOON (45004-0)",
    "created": "2025-12-18T00:00:00Z",
    "updated": "2025-12-18T00:00:00Z",
    "description": "The station was originally registered based on WMO Pub 9 Vol A information containing these observation remarks: AUT;CLIMAT(C);EVAP;GAMMA RAY;GUAN;OZONE;RAD;RADSAMP;RBCN;RBSN(T);SOILTEMP;SUNDUR (see code table A for explanations). These remarks imply the following additional observations that could not be registered automatically: Gamma ray measurements; Ozone observations; Radiation measurements; Radioactive sampling.",
    "contacts": [
      {
        "organization": "Hong Kong Observatory",
        "roles": [
          "owner"
        ]
      },
      {
        "name": "LEE,Olivia S M,Ms",
        "organization": "Hong Kong Observatory",
        "phones": [
          {
            "value": "+852 29268414"
          }
        ],
        "emails": [
          {
            "value": "olee@hko.gov.hk"
          }
        ],
        "addresses": [
          {
            "deliveryPoint": [
              "Hong Kong Observatory 134A Nathan Road, Kowloon"
            ],
            "city": "Hong Kong",
            "country": "HKG"
          }
        ],
        "roles": [
          "pointOfContact"
        ]
      },
      {
        "name": "PAN,Chi-kin,Dr",
        "organization": "Hong Kong Observatory",
        "phones": [
          {
            "value": "+852 2926 8357"
          }
        ],
        "emails": [
          {
            "value": "ckpan@hko.gov.hk"
          }
        ],
        "addresses": [
          {
            "deliveryPoint": [
              "Hong Kong Observatory 134A Nathan Road"
            ],
            "city": "Kowloon",
            "country": "HKG"
          }
        ],
        "roles": [
          "pointOfContact"
        ]
      },
      {
        "name": "LEE,Eunice Fung-ying,Ms",
        "organization": "Hong Kong Observatory",
        "phones": [
          {
            "value": "+852 29268414"
          }
        ],
        "emails": [
          {
            "value": "fylee@hko.gov.hk"
          }
        ],
        "addresses": [
          {
            "deliveryPoint": [
              "Hong Kong Observatory, 134A, Nathan Road, Kowloon, Hong Kong, China"
            ],
            "city": "Kowloon",
            "country": "HKG"
          }
        ],
        "roles": [
          "pointOfContact"
        ]
      },
      {
        "organization": "World Meteorological Organization WMO and Federal Office for Meteorology and Climatology MeteoSwiss",
        "emails": [
          {
            "value": "oscar@wmo.int"
          }
        ],
        "links": [
          {
            "href": "https://oscar.wmo.int/surface",
            "rel": "about",
            "type": "text/html"
          }
        ]
      }
    ],
    "keywords": [
      "0-20000-0-45004",
      "KOWLOON (45004-0)"
    ],
    "facilityType": "landFixed",
    "wmoRegion": "asia",
    "temporalTerritory": [
      {
        "territory": "HKG",
        "date": "2016-04-28"
      }
    ],
    "temporalProgramAffiliation": [
      {
        "programAffiliation": "CLIMATc",
        "reportingStatus": "operational",
        "date": "2016-04-28"
      },
      {
        "programAffiliation": "GOSGeneral",
        "reportingStatus": "operational",
        "date": "2016-04-28"
      },
      {
        "programAffiliation": "GUAN",
        "reportingStatus": "operational",
        "date": "2016-04-28"
      },
      {
        "programAffiliation": "RBCN",
        "reportingStatus": "operational",
        "date": "2016-04-28"
      },
      {
        "programAffiliation": "RBSNt",
        "reportingStatus": "operational",
        "date": "2016-04-28"
      },
      {
        "programAffiliation": "CLIMATc",
        "reportingStatus": "closed",
        "date": "2022-06-07"
      },
      {
        "programAffiliation": "RBCN",
        "reportingStatus": "closed",
        "date": "2022-06-07"
      },
      {
        "programAffiliation": "RBON",
        "reportingStatus": "operational",
        "date": "2022-06-07"
      },
      {
        "programAffiliation": "RBSNt",
        "reportingStatus": "closed",
        "date": "2022-06-07"
      },
      {
        "programAffiliation": "GBON",
        "reportingStatus": "operational",
        "date": "2022-09-08"
      },
      {
        "programAffiliation": "centennialObservingstations",
        "date": ".."
      }
    ],
    "schedules": [
      {
        "@type": "Event",
        "start": "0001-01-01T18:00:00",
        "timeZone": "UTC",
        "duration": "P1D",
        "recurrenceRules": [
          {
            "@type": "RecurrenceRule",
            "frequency": "daily"
          }
        ],
        "wmo.int:aggregation": {
          "temporalAggregate": "PT1H",
          "diurnalBaseTime": "00:00:00"
        },
        "uid": "schedule_f3cb664fd4ad"
      },
      {
        "@type": "Event",
        "start": "0001-01-01T16:00:00",
        "timeZone": "UTC",
        "duration": "P1D",
        "recurrenceRules": [
          {
            "@type": "RecurrenceRule",
            "frequency": "daily"
          }
        ],
        "wmo.int:aggregation": {
          "temporalAggregate": "PT12H"
        },
        "uid": "schedule_050d93af5f80"
      },
      {
        "@type": "Event",
        "start": "0001-01-01T00:00:00",
        "timeZone": "UTC",
        "duration": "P1D",
        "recurrenceRules": [
          {
            "@type": "RecurrenceRule",
            "frequency": "daily"
          }
        ],
        "wmo.int:aggregation": {
          "temporalAggregate": "PT12H"
        },
        "uid": "schedule_4023f276f03f"
      }
    ],
    "observations": [
      {
        "id": "observation:213",
        "title": "domain: atmosphere; geometry: point; variable: 213",
        "time": {
          "interval": [
            "2016-04-29",
            ".."
          ]
        },
        "observedProperty": 213,
        "observedGeometry": "point",
        "domain": {
          "domainName": "atmosphere"
        },
        "programAffiliations": [
          "RBON",
          "RBCN"
        ],
        "deployments": [
          "deployment:id_9b43c01b-4326-45a9-87a7-d7f426e5bbff"
        ],
        "reporting": {
          "internationalExchange": [
            false
          ],
          "temporalAggregate": [
            "PT1H"
          ],
          "uom": [
            "unknown"
          ],
          "dataPolicy": [
            {
              "attribution": {
                "originator": {
                  "role": null
                }
              }
            }
          ]
        }
      },
      {
        "id": "observation:216",
        "title": "domain: atmosphere; geometry: point; variable: 216",
        "time": {
          "interval": [
            "1999-05-19",
            ".."
          ]
        },
        "observedProperty": 216,
        "observedGeometry": "point",
        "domain": {
          "domainName": "atmosphere"
        },
        "programAffiliations": [
          "GUAN",
          "centennialObservingstations"
        ],
        "deployments": [
          "deployment:id_a7015e0a-ccf5-415c-85ed-d6f56b472501"
        ],
        "reporting": {
          "internationalExchange": [
            false
          ],
          "temporalAggregate": [
            "PT12H"
          ],
          "uom": [
            "unknown"
          ],
          "dataPolicy": [
            {
              "attribution": {
                "originator": {
                  "role": null
                }
              }
            }
          ],
          "referenceDatum": [
            {
              "VerticalDatum": {
                "id": "id_3addf923-3800-4454-bf33-1d3fa042602e",
                "remarks": "mean sea level",
                "scope": null
              }
            }
          ]
        }
      },
      {
        "id": "observation:224",
        "title": "domain: atmosphere; geometry: point; variable: 224",
        "time": {
          "interval": [
            "1992-07-01",
            ".."
          ]
        },
        "observedProperty": 224,
        "observedGeometry": "point",
        "domain": {
          "domainName": "atmosphere"
        },
        "programAffiliations": [
          "RBCN",
          "GUAN",
          "centennialObservingstations",
          "RBON"
        ],
        "deployments": [
          "deployment:id_f87f0b27-dd5f-47b8-8e39-d7b45f1bfba9"
        ],
        "reporting": {
          "internationalExchange": [
            false
          ],
          "temporalAggregate": [
            "PT12H"
          ],
          "uom": [
            "unknown"
          ],
          "dataPolicy": [
            {
              "attribution": {
                "originator": {
                  "role": null
                }
              }
            }
          ]
        }
      },
      {
        "id": "observation:225",
        "title": "domain: atmosphere; geometry: point; variable: 225",
        "time": {
          "interval": [
            "1992-07-01",
            ".."
          ]
        },
        "observedProperty": 225,
        "observedGeometry": "point",
        "domain": {
          "domainName": "atmosphere"
        },
        "programAffiliations": [
          "GUAN",
          "RBCN",
          "centennialObservingstations",
          "RBON"
        ],
        "deployments": [
          "deployment:id_b074e829-f661-7937-e053-148ef98d6de4"
        ],
        "reporting": {
          "internationalExchange": [
            false
          ],
          "temporalAggregate": [
            "PT12H"
          ],
          "dataPolicy": [
            {
              "attribution": {
                "originator": {
                  "role": null
                }
              }
            }
          ]
        }
      },
      {
        "id": "observation:227",
        "title": "domain: atmosphere; geometry: verticalProfile; variable: 227",
        "observedProperty": 227,
        "observedGeometry": "verticalProfile",
        "domain": {
          "domainName": "atmosphere"
        },
        "programAffiliations": [
          "GUAN",
          "RBSNt",
          "centennialObservingstations",
          "RBON",
          "GBON"
        ],
        "deployments": [
          "deployment:id_01f56dfe-5bdb-4147-9604-0eb685e7e9de"
        ]
      },
      {
        "id": "observation:227",
        "title": "domain: atmosphere; geometry: verticalProfile; variable: 227",
        "time": {
          "interval": [
            "2004-05-24",
            ".."
          ]
        },
        "observedProperty": 227,
        "observedGeometry": "verticalProfile",
        "domain": {
          "domainName": "atmosphere"
        },
        "programAffiliations": [
          "GUAN",
          "RBSNt",
          "centennialObservingstations",
          "RBON",
          "GBON"
        ],
        "deployments": [
          "deployment:id_b074e829-f660-7937-e053-148ef98d6de4"
        ],
        "reporting": {
          "internationalExchange": [
            true
          ],
          "temporalAggregate": [
            "PT12H"
          ],
          "dataPolicy": [
            {
              "attribution": {
                "originator": {
                  "role": null
                }
              }
            }
          ]
        }
      },
      {
        "id": "observation:12249",
        "title": "domain: atmosphere; geometry: point; variable: 12249",
        "time": {
          "interval": [
            "2016-04-29",
            "2016-04-30"
          ]
        },
        "observedProperty": 12249,
        "observedGeometry": "point",
        "domain": {
          "domainName": "atmosphere"
        },
        "programAffiliations": [
          "CLIMATc",
          "RBCN",
          "centennialObservingstations",
          "RBON"
        ],
        "deployments": [
          "deployment:id_65929544-483b-438c-bbfb-31c45b550779"
        ],
        "reporting": {
          "internationalExchange": [
            false
          ],
          "temporalAggregate": [
            "PT1H"
          ],
          "uom": [
            "unknown"
          ],
          "dataPolicy": [
            {
              "attribution": {
                "originator": {
                  "role": null
                }
              }
            }
          ]
        }
      },
      {
        "id": "observation:256",
        "title": "domain: atmosphere; geometry: verticalProfile; variable: 256",
        "time": {
          "interval": [
            "2020-10-09",
            ".."
          ]
        },
        "observedProperty": 256,
        "observedGeometry": "verticalProfile",
        "domain": {
          "domainName": "atmosphere"
        },
        "programAffiliations": [
          "RBON",
          "RBSNt",
          "GBON"
        ],
        "deployments": [
          "deployment:id_bd1f51be-f8c8-4340-8881-a2edd92a6027"
        ],
        "reporting": {
          "internationalExchange": [
            false
          ],
          "temporalAggregate": [
            "P1D"
          ],
          "uom": [
            "unknown"
          ],
          "dataPolicy": [
            {
              "attribution": {
                "originator": {
                  "role": null
                }
              }
            }
          ]
        }
      },
      {
        "id": "observation:270",
        "title": "domain: atmosphere; geometry: point; variable: 270",
        "observedProperty": 270,
        "observedGeometry": "point",
        "domain": {
          "domainName": "atmosphere"
        },
        "programAffiliations": [
          "RBON",
          "CLIMATc",
          "RBCN"
        ],
        "deployments": [
          "deployment:id_54b9a950-2b00-43c9-9d19-0d6506dde229"
        ]
      },
      {
        "id": "observation:310",
        "title": "domain: atmosphere; geometry: verticalProfile; variable: 310",
        "time": {
          "interval": [
            "2004-05-24",
            ".."
          ]
        },
        "observedProperty": 310,
        "observedGeometry": "verticalProfile",
        "domain": {
          "domainName": "atmosphere"
        },
        "programAffiliations": [
          "GUAN",
          "RBSNt",
          "centennialObservingstations",
          "RBON",
          "GBON"
        ],
        "deployments": [
          "deployment:id_b6631357-a24d-48d2-92c0-c6eed97c2291"
        ],
        "reporting": {
          "internationalExchange": [
            true
          ],
          "temporalAggregate": [
            "PT12H"
          ],
          "uom": [
            "unknown"
          ],
          "dataPolicy": [
            {
              "attribution": {
                "originator": {
                  "role": null
                }
              }
            }
          ]
        }
      },
      {
        "id": "observation:510",
        "title": "domain: terrestrial; geometry: area; variable: 510",
        "observedProperty": 510,
        "observedGeometry": "area",
        "domain": {
          "domainName": "terrestrial"
        },
        "programAffiliations": [
          "GOSGeneral"
        ],
        "deployments": [
          "deployment:id_9a56a45a-9a10-4aa5-be1f-53c3d137ed5f"
        ]
      },
      {
        "id": "observation:596",
        "title": "domain: terrestrial; geometry: unknown; variable: 596",
        "observedProperty": 596,
        "observedGeometry": "unknown",
        "domain": {
          "domainName": "terrestrial"
        },
        "programAffiliations": [
          "GOSGeneral"
        ],
        "deployments": [
          "deployment:id_5f6f77ba-1cb8-4738-b86b-4d5cf6d6aa75"
        ]
      },
      {
        "id": "observation:12000",
        "title": "domain: atmosphere; geometry: verticalProfile; variable: 12000",
        "time": {
          "interval": [
            "2004-05-24",
            ".."
          ]
        },
        "observedProperty": 12000,
        "observedGeometry": "verticalProfile",
        "domain": {
          "domainName": "atmosphere"
        },
        "programAffiliations": [
          "RBSNt",
          "GUAN",
          "centennialObservingstations",
          "RBON",
          "GBON"
        ],
        "deployments": [
          "deployment:id_bd3ebd7b-8158-4f66-ad37-34fb718d8498"
        ],
        "reporting": {
          "internationalExchange": [
            true
          ],
          "temporalAggregate": [
            "PT12H"
          ],
          "uom": [
            "unknown"
          ],
          "dataPolicy": [
            {
              "attribution": {
                "originator": {
                  "role": null
                }
              }
            }
          ]
        }
      },
      {
        "id": "observation:12005",
        "title": "domain: atmosphere; geometry: point; variable: 12005",
        "time": {
          "interval": [
            "2016-07-14",
            ".."
          ]
        },
        "observedProperty": 12005,
        "observedGeometry": "point",
        "domain": {
          "domainName": "atmosphere"
        },
        "programAffiliations": [
          "RBCN",
          "GUAN",
          "centennialObservingstations",
          "RBON"
        ],
        "deployments": [
          "deployment:id_46214214-6805-4ce1-87ac-880b6f691c24"
        ],
        "reporting": {
          "internationalExchange": [
            false
          ],
          "temporalAggregate": [
            "PT12H"
          ],
          "uom": [
            "unknown"
          ],
          "dataPolicy": [
            {
              "attribution": {
                "originator": {
                  "role": null
                }
              }
            }
          ]
        }
      },
      {
        "id": "observation:12006",
        "title": "domain: atmosphere; geometry: point; variable: 12006",
        "time": {
          "interval": [
            "2016-07-14",
            ".."
          ]
        },
        "observedProperty": 12006,
        "observedGeometry": "point",
        "domain": {
          "domainName": "atmosphere"
        },
        "programAffiliations": [
          "RBON",
          "RBCN",
          "GUAN",
          "centennialObservingstations"
        ],
        "deployments": [
          "deployment:cca8c9b3-3597-23ea-e053-148ef98d1a71"
        ],
        "reporting": {
          "internationalExchange": [
            false
          ],
          "temporalAggregate": [
            "PT12H"
          ],
          "uom": [
            "unknown"
          ],
          "dataPolicy": [
            {
              "attribution": {
                "originator": {
                  "role": null
                }
              }
            }
          ]
        }
      }
    ],
    "deployments": [
      {
        "id": "deployment:id_9b43c01b-4326-45a9-87a7-d7f426e5bbff",
        "time": {
          "interval": [
            "2016-04-29",
            ".."
          ]
        },
        "observingMethod": "unknown",
        "representativeness": "toposcale",
        "referenceSurface": "other",
        "verticalDistanceFromReferenceSurface": [
          {
            "value": 2.0,
            "uom": "m"
          }
        ],
        "temporalOfficialStatus": [
          {
            "officialStatus": "unknown",
            "date": "2016-04-29"
          }
        ],
        "temporalObservingSchedule": [
          {
            "observingSchedule": "schedule_f3cb664fd4ad",
            "date": "2016-04-29"
          }
        ]
      },
      {
        "id": "deployment:id_b074e829-f661-7937-e053-148ef98d6de4",
        "time": {
          "interval": [
            "1992-07-01",
            ".."
          ]
        },
        "sourceOfObservation": "automaticReading",
        "observingMethod": 188,
        "referenceSurface": "other",
        "verticalDistanceFromReferenceSurface": [
          {
            "value": 67.0,
            "uom": "m"
          }
        ],
        "temporalOfficialStatus": [
          {
            "officialStatus": "unknown",
            "date": "1992-07-01"
          }
        ],
        "keywords": [
          "automaticReading"
        ],
        "temporalObservingSchedule": [
          {
            "observingSchedule": "schedule_050d93af5f80",
            "date": "1992-07-01"
          }
        ]
      },
      {
        "id": "deployment:id_01f56dfe-5bdb-4147-9604-0eb685e7e9de",
        "observingMethod": 331,
        "representativeness": "mesoscale",
        "temporalOfficialStatus": [
          {
            "officialStatus": "unknown",
            "date": ".."
          }
        ]
      },
      {
        "id": "deployment:id_b074e829-f660-7937-e053-148ef98d6de4",
        "time": {
          "interval": [
            "2004-05-24",
            ".."
          ]
        },
        "sourceOfObservation": "automaticReading",
        "observingMethod": 331,
        "instrument": [
          "instrument:188f77ff7d66"
        ],
        "temporalSerialNumber": [
          {
            "serialNumber": "not applicable",
            "date": "2004-05-24"
          }
        ],
        "referenceSurface": "other",
        "verticalDistanceFromReferenceSurface": [
          {
            "value": 66.0,
            "uom": "m"
          }
        ],
        "temporalOfficialStatus": [
          {
            "officialStatus": "unknown",
            "date": "2004-05-24"
          }
        ],
        "keywords": [
          "Vaisala Oyj",
          "RS41-SG",
          "not applicable",
          "automaticReading"
        ],
        "temporalObservingSchedule": [
          {
            "observingSchedule": "schedule_4023f276f03f",
            "date": "2004-05-24"
          }
        ]
      },
      {
        "id": "deployment:id_54b9a950-2b00-43c9-9d19-0d6506dde229",
        "observingMethod": "unknown",
        "representativeness": "toposcale",
        "temporalOfficialStatus": [
          {
            "officialStatus": "unknown",
            "date": ".."
          }
        ]
      },
      {
        "id": "deployment:id_9a56a45a-9a10-4aa5-be1f-53c3d137ed5f",
        "observingMethod": "unknown",
        "representativeness": "toposcale",
        "temporalOfficialStatus": [
          {
            "officialStatus": "unknown",
            "date": ".."
          }
        ]
      },
      {
        "id": "deployment:id_5f6f77ba-1cb8-4738-b86b-4d5cf6d6aa75",
        "observingMethod": "unknown",
        "representativeness": "toposcale",
        "temporalOfficialStatus": [
          {
            "officialStatus": "unknown",
            "date": ".."
          }
        ]
      },
      {
        "id": "deployment:id_bd3ebd7b-8158-4f66-ad37-34fb718d8498",
        "time": {
          "interval": [
            "2004-05-24",
            ".."
          ]
        },
        "sourceOfObservation": "automaticReading",
        "observingMethod": 327,
        "instrument": [
          "instrument:188f77ff7d66"
        ],
        "temporalSerialNumber": [
          {
            "serialNumber": "NOT APPLICABLE",
            "date": "2004-05-24"
          }
        ],
        "representativeness": "mesoscale",
        "referenceSurface": "localGround",
        "verticalDistanceFromReferenceSurface": [
          {
            "value": 0.0,
            "uom": "m"
          }
        ],
        "temporalOfficialStatus": [
          {
            "officialStatus": "unknown",
            "date": "2004-05-24"
          }
        ],
        "keywords": [
          "Vaisala Oyj",
          "RS41-SG",
          "NOT APPLICABLE",
          "automaticReading"
        ],
        "temporalObservingSchedule": [
          {
            "observingSchedule": "schedule_4023f276f03f",
            "date": "2004-05-24"
          }
        ]
      }
    ],
    "instruments": [
      {
        "id": "instrument:188f77ff7d66",
        "manufacturer": "Vaisala Oyj",
        "model": "RS41-SG"
      }
    ]
  }
}
